django3_auth_saml2/__init__.py
django3_auth_saml2/backends.py
django3_auth_saml2/config.py
django3_auth_saml2/consts.py
django3_auth_saml2/urls.py
django3_auth_saml2/views.py
django3_auth_saml2-0.6.1.dist-info/METADATA
django3_auth_saml2-0.6.1.dist-info/WHEEL
django3_auth_saml2-0.6.1.dist-info/top_level.txt
django3_auth_saml2-0.6.1.dist-info/RECORD
