Metadata-Version: 2.1
Name: django3-auth-saml2
Version: 0.6.1
Summary: Django3 auth SAML2 integration
Home-page: UNKNOWN
Author: Jeremy Schulman
License: Apache 2.0
Platform: UNKNOWN
Classifier: Development Status :: 5 - Production/Stable
Classifier: Intended Audience :: Developers
Classifier: Topic :: Software Development :: Libraries :: Python Modules
Classifier: License :: OSI Approved :: Apache Software License
Classifier: Framework :: Django :: 3.0
Classifier: Programming Language :: Python :: 3.6
Requires-Dist: django (>=3)
Requires-Dist: pysaml2 (>=6.5.0)
